webbench
