Metadata-Version: 1.1
Name: webbench
Version: 1.0.2
Summary: lightweight HTTP/HTTPS benchmark tool written on Python
Home-page: https://github.com/arozumenko/pybench
Author: Artem Rozumenko
Author-email: artem.rozumenko@gmail.com
License: MIT License
Platform: UNKNOWN
Classifier: Development Status :: 5 - Production/Stable
Classifier: Environment :: Console
Classifier: Intended Audience :: Developers
Classifier: License :: OSI Approved :: MIT License
Classifier: Programming Language :: Python :: 2.7
Classifier: Topic :: Internet :: WWW/HTTP
Classifier: Topic :: Software Development :: Quality Assurance
Classifier: Topic :: Software Development :: Testing
Classifier: Topic :: Software Development :: Testing :: Traffic Generation
Classifier: Topic :: Utilities
